hotbox/__init__.py
hotbox/_types.py
hotbox/api.py
hotbox/app.py
hotbox/const.py
hotbox/ec2.py
hotbox/gunicorn_conf.py
hotbox/py.typed
hotbox/settings.py
hotbox/templates.py
hotbox/utils.py
hotbox/cli/__init__.py
hotbox/cli/create.py
hotbox/cli/delete.py
hotbox/cli/get.py
hotbox/cli/main.py
hotbox/cli/server.py
hotbox-0.0.40.dist-info/LICENSE
hotbox-0.0.40.dist-info/METADATA
hotbox-0.0.40.dist-info/WHEEL
hotbox-0.0.40.dist-info/entry_points.txt
hotbox-0.0.40.dist-info/top_level.txt
hotbox-0.0.40.dist-info/RECORD
