Metadata-Version: 2.1
Name: hotbox
Version: 0.0.40
Summary: hotbox
Author-email: Anthony Corletti <anthcor@gmail.com>
License: See LICENSE
Project-URL: Documentation, https://github.com/anthonycorletti/hotbox
Requires-Python: >=3.8
License-File: LICENSE
Requires-Dist: boto3 >=1.20.10
Requires-Dist: fastapi >=0.70.0
Requires-Dist: httpx >=0.21.1
Requires-Dist: gunicorn >=20.1.0
Requires-Dist: jinja2 >=3.0.2
Requires-Dist: orjson >=3.6.4
Requires-Dist: pydantic >=1.8.2
Requires-Dist: pydantic-settings >=0.4.0
Requires-Dist: python-dotenv >=0.19.1
Requires-Dist: python-multipart >=0.0.5
Requires-Dist: rich >=10.12.0
Requires-Dist: typer >=0.4.0
Requires-Dist: uvicorn >=0.15.0
Provides-Extra: dev
Requires-Dist: black >=21.10b0 ; extra == 'dev'
Requires-Dist: coverage >=6.1.1 ; extra == 'dev'
Requires-Dist: invoke >=1.6.0 ; extra == 'dev'
Requires-Dist: mdx-include >=1.4.2 ; extra == 'dev'
Requires-Dist: mkdocs >=1.4.2 ; extra == 'dev'
Requires-Dist: mkdocs-material >=9.1.5 ; extra == 'dev'
Requires-Dist: mypy <1.1.1 ; extra == 'dev'
Requires-Dist: packaging >=21.0 ; extra == 'dev'
Requires-Dist: pre-commit >=2.17.0 ; extra == 'dev'
Requires-Dist: pytest >=6.2.5 ; extra == 'dev'
Requires-Dist: pytest-asyncio >=0.20.3 ; extra == 'dev'
Requires-Dist: pytest-cov >=3.0.0 ; extra == 'dev'
Requires-Dist: ruff >=0.0.98 ; extra == 'dev'
